dnsproxy/__init__.py
dnsproxy/client.py
dnsproxy/server.py
dnsproxy/utils.py
dnsproxy-0.3.2.dist-info/DESCRIPTION.rst
dnsproxy-0.3.2.dist-info/METADATA
dnsproxy-0.3.2.dist-info/RECORD
dnsproxy-0.3.2.dist-info/WHEEL
dnsproxy-0.3.2.dist-info/entry_points.txt
dnsproxy-0.3.2.dist-info/metadata.json
dnsproxy-0.3.2.dist-info/top_level.txt
